deeptissueunet/package/README.md
deeptissueunet/package/Unet_2plus/UNet_2Plus.py
deeptissueunet/package/Unet_2plus/__init__.py
deeptissueunet/package/Unet_2plus/init_weights.py
deeptissueunet/package/Unet_2plus/layers.py
deeptissueunet/package/__init__.py
deeptissueunet/package/data.py
deeptissueunet/package/losses.py
deeptissueunet/package/predict.py
deeptissueunet/package/requirements.txt
deeptissueunet/package/train.py
deeptissueunet/package/unet.py
deeptissueunet/package/utils.py
deeptissueunet/siam_package/README.md
deeptissueunet/siam_package/__init__.py
deeptissueunet/siam_package/data.py
deeptissueunet/siam_package/helpers/average_tifs.py
deeptissueunet/siam_package/helpers/compare_tif_files.py
deeptissueunet/siam_package/helpers/cpu_count.py
deeptissueunet/siam_package/helpers/create_pixel_value_histogram.py
deeptissueunet/siam_package/helpers/cuda_test.py
deeptissueunet/siam_package/helpers/extract_frame_of_movie.py
deeptissueunet/siam_package/helpers/find_frame_of_image.py
deeptissueunet/siam_package/helpers/generate_plain_image.py
deeptissueunet/siam_package/helpers/generate_siam_unet_input_imgs.py
deeptissueunet/siam_package/helpers/low_mem_tif_utils.py
deeptissueunet/siam_package/helpers/md5sum.py
deeptissueunet/siam_package/helpers/threshold_images.py
deeptissueunet/siam_package/helpers/tif_to_mp4.py
deeptissueunet/siam_package/helpers/util.py
deeptissueunet/siam_package/losses.py
deeptissueunet/siam_package/predict.py
deeptissueunet/siam_package/siam_unet.py
deeptissueunet/siam_package/train.py
deeptissueunet-0.1.16.dist-info/WHEEL
deeptissueunet-0.1.16.dist-info/METADATA
deeptissueunet-0.1.16.dist-info/RECORD
