Metadata-Version: 2.1
Name: deeptissueunet
Version: 0.1.16
Summary: 
License: MIT
Author: Yuxi Long
Author-email: longyuxi@live.com
Requires-Python: >=3.8,<4.0
Classifier: License :: OSI Approved :: MIT License
Classifier: Programming Language :: Python :: 3
Classifier: Programming Language :: Python :: 3.8
Classifier: Programming Language :: Python :: 3.9
Requires-Dist: albumentations
Requires-Dist: barbar
Requires-Dist: matplotlib
Requires-Dist: numpy
Requires-Dist: opencv-python
Requires-Dist: scikit-image (>=0.18.2,<0.19.0)
Requires-Dist: scikit_image
Requires-Dist: tifffile
Requires-Dist: torch (>=1.9.0,<2.0.0)
Requires-Dist: tqdm
Requires-Dist: wandb
